{
  "recentFiles": [
    {
      "basename": "java-stream",
      "path": "md/java-stream.md"
    },
    {
      "basename": "java-函数式编程库",
      "path": "md/java-函数式编程库.md"
    },
    {
      "basename": "dom4j",
      "path": "md/dom4j.md"
    },
    {
      "basename": "linux常用命令",
      "path": "md/linux常用命令.md"
    },
    {
      "basename": "common-configuration",
      "path": "md/common-configuration.md"
    },
    {
      "basename": "java-string",
      "path": "md/java-string.md"
    },
    {
      "basename": "regex",
      "path": "md/regex.md"
    },
    {
      "basename": "java-utils",
      "path": "md/java-utils.md"
    },
    {
      "basename": "java_app_一些常用的应用",
      "path": "md/java_app_一些常用的应用.md"
    },
    {
      "basename": "common_常用",
      "path": "md/common_常用.md"
    },
    {
      "basename": "maven",
      "path": "md/maven.md"
    },
    {
      "basename": "cheatsheet_快捷键",
      "path": "md/cheatsheet_快捷键.md"
    },
    {
      "basename": "obsidan",
      "path": "md/obsidan.md"
    },
    {
      "basename": "shell-tips",
      "path": "md/shell-tips.md"
    },
    {
      "basename": "git",
      "path": "md/git.md"
    }
  ],
  "omittedPaths": [],
  "maxLength": 15
}